{
  "fixes": [
    {"subject_id": "007", "num": 3, "fixed_answer": "リスク管理部門は業務ラインから独立した組織として位置づけ、営業部門とは権限と責任を明確に分離して、牽制機能を発揮することが不可欠である"},
    {"subject_id": "007", "num": 5, "fixed_answer": "不正を行った個人だけでなく、その個人が属する法人にも罰金刑が科せられる場合がある規定"},
    {"subject_id": "007", "num": 6, "fixed_answer": "情報自体は財物にあたらないが、情報が記載された紙媒体やUSBメモリ等の有体物を無断で持ち出した場合は窃盗罪が成立する"},
    {"subject_id": "007", "num": 7, "fixed_answer": "お客さまや取引先への詐欺だけでなく、会社に虚偽の申告をして不当に費用を支出させる行為も会社に対する詐欺に該当する"},
    {"subject_id": "007", "num": 9, "fixed_answer": "背任罪は他人のために事務を処理する者がその任務に背いて本人に財産上の損害を加えた場合に成立し、取締役等の場合はより重い特別背任罪となる"},
    {"subject_id": "007", "num": 10, "fixed_answer": "贈賄罪は供与・供与の申込み・供与の約束のいずれでも成立し、賄賂には接待や斡旋等の非財産的利益も含まれる広い概念である"},
    {"subject_id": "007", "num": 13, "fixed_answer": "行為者は10年以下の拘禁刑もしくは2,000万円以下の罰金に処され、法人にも5億円以下の罰金刑（法人両罰）が科される"},
    {"subject_id": "007", "num": 14, "fixed_answer": "マスメディアが「一対多数」の情報伝達であるのに対し、SNSは「多数対多数」で瞬時に情報が広範囲に拡散する特性を持つ"},
    {"subject_id": "007", "num": 15, "fixed_answer": "個人のアカウントの発信でも所属企業名が推測できる場合等は企業の信用・資産に影響し得るため、会社は教育・指導・警告等の統制を行うことが求められる"},
    {"subject_id": "007", "num": 16, "fixed_answer": "信用毀損罪・業務妨害罪は、虚偽の風説の流布や偽計により人の信用を毀損し、またはその業務を妨害する行為であり、他社を貶める虚偽投稿が該当する"},
    {"subject_id": "007", "num": 18, "fixed_answer": "「労働者等」には正社員・派遣労働者・アルバイト・公務員のほか、退職から1年以内の退職者や取締役・監査役等の役員も含まれる"},
    {"subject_id": "007", "num": 19, "fixed_answer": "「事業者内部」「権限を有する行政機関」「その他の事業者外部（報道機関・消費者団体等）」"},
    {"subject_id": "007", "num": 21, "fixed_answer": "事業者内部への通報は「思料すること」で足りるが、行政機関への通報には「信ずるに足りる相当の理由」が必要で、企業外通報の方が要件が厳しい"},
    {"subject_id": "007", "num": 23, "fixed_answer": "公益通報者の範囲にフリーランスが追加され、通報後1年以内の解雇・懲戒を公益通報を理由と推定する立証責任の転換等が導入された"},
    {"subject_id": "007", "num": 24, "fixed_answer": "経営陣が「コンプライアンス・リスク管理は経営の根幹をなす」という意識を持って主体的に考え、その姿勢を役職員全員に浸透させることが重要である"},
    {"subject_id": "007", "num": 25, "fixed_answer": "代理店の役職員等の行動により、顧客保護に悪影響を与えたり市場の公正性を損なったり自社の評判が毀損し損失を被るおそれのあるリスクをいう"},
    {"subject_id": "007", "num": 27, "fixed_answer": "システムのダウンや誤作動等の不備、またはコンピュータの不正使用により、お客さまや代理店が損失を被るリスク"},
    {"subject_id": "007", "num": 33, "fixed_answer": "情報自体は財物ではないため窃盗罪にはあたらないが、不正競争防止法により営業秘密の侵害行為として刑罰が科される場合がある"},
    {"subject_id": "007", "num": 34, "fixed_answer": "この行為は業務上横領罪・背任罪・不正競争防止法違反に該当し得るため、直ちにコンプライアンス統括部門に報告し、USBの使用停止と事実確認を行う"},
    {"subject_id": "007", "num": 35, "fixed_answer": "「信ずるに足りる相当の理由」に加え、不利益取扱いを受けるおそれや証拠隠滅のおそれ等、複数の要件のいずれか1つを満たすことが必要である"},
    {"subject_id": "007", "num": 37, "fixed_answer": "文書偽造罪は「行使の目的」で文書・図画を「偽造する」ことで成立し、公文書偽造罪や私文書偽造等罪など5つの類型がある"},
    {"subject_id": "007", "num": 40, "fixed_answer": "災害や保険会社内部・外部に起因するシステム障害等が発生した場合に備えて策定しておく緊急時体制のことである"},
    {"subject_id": "007", "num": 41, "fixed_answer": "「事務リスク」「システムリスク」「その他オペレーショナル・リスク（法務リスク・人的リスク・風評リスク）」"},
    {"subject_id": "007", "num": 42, "fixed_answer": "再発防止策を単なる「フローの追加」で終わらせず、発生原因を企業文化まで遡って検証し是正できるようにすることが求められる"},
    {"subject_id": "007", "num": 43, "fixed_answer": "全ての業務に事務リスクが存在することを理解して管理態勢を整備し、個人情報の漏えいや架空契約等の不正を防止する措置を講じる"},
    {"subject_id": "007", "num": 46, "fixed_answer": "「顧客本位」が営業現場で実践できているかをアンケート調査等で定点観測し、その結果を取締役会等へ報告することが有効である"},
    {"subject_id": "007", "num": 48, "fixed_answer": "事業部門はリスクの発生源であるため第1ラインとしての責任を果たし、役職員自身が管理責任を担うという意識を持って業務を行う必要がある"},
    {"subject_id": "007", "num": 49, "fixed_answer": "役員の場合、公益通報を理由とする解任は無効とはならないが、解任によって生じた損害の賠償を事業者に請求できる"},
    {"subject_id": "007", "num": 50, "fixed_answer": "商品販売状況等を公開し、手数料差等がお客さまへの提案商品に影響しないことを定期的にレビューするなど、利益相反管理を実施する"},

    {"subject_id": "009", "num": 1, "fixed_answer": "2008年の金融商品取引法改正で、利益相反による弊害の防止を目的として義務付けられ、同時に銀行法・保険業法も改正された"},
    {"subject_id": "009", "num": 3, "fixed_answer": "①顧客と金融事業者の利益が相反するおそれのある取引、②顧客の利益が他の顧客の不利益となるおそれのある取引、③顧客情報を同意なく不当に利用する取引、④その他顧客の利益が不当に害されるおそれのある取引"},
    {"subject_id": "009", "num": 10, "fixed_answer": "この行為は「顧客の利益と代理店の利益が相反する行為」に該当し、お客さまの利益を損ねるため、適切な利益相反管理を行う必要がある"},
    {"subject_id": "009", "num": 11, "fixed_answer": "利益相反管理方針や利益相反があった場合の事実を書面・ポスター掲示・ホームページ掲載等で開示し、お客さまへの透明性を確保する"},
    {"subject_id": "009", "num": 12, "fixed_answer": "利益相反管理部署は対象取引に該当するおそれのある事象の情報を収集して一元的に管理し、定期的に経営陣・内部監査部門に連携する"},
    {"subject_id": "009", "num": 13, "fixed_answer": "利益相反の可能性を正確に把握し、可能性がある場合は適切に管理して、具体的な対応方針をあらかじめ策定しておく必要がある"},
    {"subject_id": "009", "num": 15, "fixed_answer": "保険業法でも、利益相反の特定や部門の分離等の体制整備、管理方針の策定・公表、記録の5年間保存が金融商品取引法と同様に義務付けられている"},
    {"subject_id": "009", "num": 19, "fixed_answer": "利益相反が生じる可能性はいたるところにあるため、どのような場合に生じ得るかをあらかじめ想定し、適切に管理する態勢を整備する必要があるから"},
    {"subject_id": "009", "num": 25, "fixed_answer": "運用部門が、法人営業部門が取引関係を有する企業を運用先に選ぶ場合、顧客の利益より取引関係を優先するおそれがあり、利益相反の考慮が必要となる"},
    {"subject_id": "009", "num": 30, "fixed_answer": "利益相反管理の実効性を継続的に維持するため、定期的な検証を通じて必要に応じ管理方法を改善・更新していくことが求められるから"},
    {"subject_id": "009", "num": 32, "fixed_answer": "利益相反管理方針を踏まえた業務運営の手続き等を社内規則として整備し、研修・教育等を通じて全ての役職員に周知徹底することが求められる"},
    {"subject_id": "009", "num": 35, "fixed_answer": "利益相反管理部署が、管理方針で規定された対象取引に該当するおそれのある事象の情報を収集し、利益相反に該当するかどうかを特定する"},
    {"subject_id": "009", "num": 37, "fixed_answer": "法令や業務慣行が変更された場合は、利益相反のおそれがある取引の特定・類型化に的確に対応し、管理態勢についても見直しを行う"},
    {"subject_id": "009", "num": 38, "fixed_answer": "お客さまのニーズを正確に把握したうえで、利益相反の可能性を適切に管理しながら、最善の商品・サービスを提案する"},
    {"subject_id": "009", "num": 41, "fixed_answer": "管理態勢の実効性について評価・検証を行い、必要に応じて方針を改訂するとともに、法令や業務慣行の変更にも対応して見直すことが重要である"},
    {"subject_id": "009", "num": 44, "fixed_answer": "平時から利益相反管理方針を整備・開示し、手数料差等が提案商品に影響しないことをレビューした結果を、透明性をもって説明できる体制を構築する"},
    {"subject_id": "009", "num": 47, "fixed_answer": "代理店外事業の収益を上げるために、保険契約者であるお客さまの情報を、承諾なしに他の事業に利用した"},
    {"subject_id": "009", "num": 48, "fixed_answer": "管理情報を経営陣・内部監査部門と共有し、経営陣による適切な判断と内部監査による独立的な検証を可能にして管理の実効性を確保するため"},
    {"subject_id": "009", "num": 50, "fixed_answer": "利益相反が生じる可能性を認識して管理方針を整備・周知し、お客さまの利益を不当に害さないよう継続的に管理態勢を維持・改善していく"},

    {"subject_id": "011", "num": 1, "fixed_answer": "公正かつ自由な競争を通じて、消費者利益の確保および国民経済の健全な発達の促進を目的としている"},
    {"subject_id": "011", "num": 3, "fixed_answer": "複数の事業者が価格・数量・販路等を協定して競争を制限する行為で、価格カルテルや入札談合が典型例であり、課徴金減免制度が適用されることがある"},
    {"subject_id": "011", "num": 5, "fixed_answer": "生命保険会社間で話し合い、他社が募集活動を行う職域に対し互いに募集活動を行わないよう申し合わせること"},
    {"subject_id": "011", "num": 9, "fixed_answer": "事業者間の公正な競争の確保や国際的約束の履行を目的に、不正競争の防止や損害賠償の措置等を講じ、国民経済の健全な発展に寄与すること"},
    {"subject_id": "011", "num": 11, "fixed_answer": "1968年制定の消費者保護基本法を大幅改正して2004年に施行され、「消費者の権利の尊重」と「自立の支援」を政策の柱としている"},
    {"subject_id": "011", "num": 13, "fixed_answer": "「事業者の損害賠償責任を免除する条項」「消費者の解除権を一方的に制限する条項」「過大なキャンセル料や違約金を定める条項」「消費者の権利を一方的に害する条項」"},
    {"subject_id": "011", "num": 15, "fixed_answer": "クーリング・オフは、多くの取引類型で法律所定の書面の受領日（または商品引渡し日）から8日または20日以内に適用される"},
    {"subject_id": "011", "num": 16, "fixed_answer": "過大な景品類の提供や不当な表示により一般消費者を不当に誘引し、その自主的・合理的な選択を阻害する行為を禁止して消費者利益を保護すること"},
    {"subject_id": "011", "num": 18, "fixed_answer": "消費者庁は調査を行い、措置命令や課徴金納付命令を行うことができ、措置命令違反には刑事罰（2年以下の拘禁刑または300万円以下の罰金等）が科され得る"},
    {"subject_id": "011", "num": 21, "fixed_answer": "生存する個人に関する情報で、氏名・生年月日等により特定の個人を識別できるものをいい、顔認証やマイナンバー等の個人識別符号も含まれる"},
    {"subject_id": "011", "num": 22, "fixed_answer": "他人に知られることで不当な差別や偏見等の不利益を被る可能性がある情報であり、特に慎重な取扱いが求められる"},
    {"subject_id": "011", "num": 25, "fixed_answer": "著作物を適法に利用するには事前に使用許諾契約の締結が必要で、新聞記事の社内配布やパンフレットの写真使用等にも許諾契約が要る"},
    {"subject_id": "011", "num": 28, "fixed_answer": "国籍、信条または社会的身分を理由として、賃金、労働時間その他の労働条件について、差別的な取扱いをしてはならない"},
    {"subject_id": "011", "num": 29, "fixed_answer": "労働者の過半数代表との労使協定で時間外・休日労働を定めて行政官庁に届け出るもので、時間外労働には上限（月45時間・年360時間）がある"},
    {"subject_id": "011", "num": 31, "fixed_answer": "6か月間で全労働日の8割以上出勤した労働者に年10日が与えられ、年数に応じ最高20日まで増え、パートタイム労働者にも付与される"},
    {"subject_id": "011", "num": 32, "fixed_answer": "結婚・妊娠・出産等を理由とする不利益取扱いは禁止され、妊娠中や産後1年以内の解雇は、それを理由としない旨を事業主が証明しない限り無効となる"},
    {"subject_id": "011", "num": 33, "fixed_answer": "上司や同僚に限らず取引先やお客さま等も行為者・被害者になり得て、性別に関係なく、同性に対するものも該当する"},
    {"subject_id": "011", "num": 34, "fixed_answer": "①優越的な関係を背景とした言動で、②業務上必要かつ相当な範囲を超え、③労働者の就業環境が害されるもの、の3要素を全て満たすもの"},
    {"subject_id": "011", "num": 39, "fixed_answer": "お客さま等のクレーム・言動のうち、要求内容の妥当性に照らし手段や態様が社会通念上不相当で、労働者の就業環境が害されるもの"},
    {"subject_id": "011", "num": 40, "fixed_answer": "①要求内容の妥当性（瑕疵がなければ正当性を欠く）と、②手段・態様の相当性（暴力的・威圧的・継続的な言動等）の2点から判断する"},
    {"subject_id": "011", "num": 41, "fixed_answer": "1972年制定で、労働者の安全と健康の確保や快適な職場環境の形成を目的とし、安全衛生管理体制の確立や危険防止措置等を事業者に義務付けている"},
    {"subject_id": "011", "num": 42, "fixed_answer": "事業者は年1回以上の定期健康診断の実施義務を負い、従業員50名以上の事業場ではストレスチェックが義務化され、高ストレス者には面接指導が求められる"},
    {"subject_id": "011", "num": 43, "fixed_answer": "労働者を使用する全事業に強制的に適用され、正社員のほかアルバイト・パート・派遣・日雇い等、賃金が支払われる労働者すべてに適用される"},
    {"subject_id": "011", "num": 44, "fixed_answer": "事実上の男女間格差を解消する目的で女性のみを対象としたり女性を有利に取り扱うこと（ポジティブ・アクション）は均等法違反にならない"},
    {"subject_id": "011", "num": 45, "fixed_answer": "具体的なパワハラに該当しなくても、放置すれば就業環境が害されるおそれがある事項は幅広く対象として、迅速かつ適切な措置を講じる"},
    {"subject_id": "011", "num": 47, "fixed_answer": "労働者が女性であることを理由として、賃金について男性と差別的な取扱い（不利な取扱いだけでなく有利な取扱いを含む）をしてはならない"},
    {"subject_id": "011", "num": 48, "fixed_answer": "基本方針や対応姿勢の明確化と従業員への周知啓発、被害従業員向けの相談体制の整備等の取り組みが考えられる"},
    {"subject_id": "011", "num": 50, "fixed_answer": "独占禁止法や個人情報保護法、労働関連法等の多様な法令を理解して適法かつ倫理的に行動し、問題発見時には速やかに報告する姿勢が求められる"}
  ]
}
